flozz_daily_mix/__init__.py
flozz_daily_mix/__main__.py
flozz_daily_mix/cli.py
flozz_daily_mix/config.py
flozz_daily_mix/db.py
flozz_daily_mix/helpers.py
flozz_daily_mix/musicbrainz_db.py
flozz_daily_mix/playlist.py
flozz_daily_mix/subsonic.py
flozz_daily_mix/data/musicbrainz_db/genre
flozz_daily_mix/data/musicbrainz_db/genre_alias
flozz_daily_mix/data/musicbrainz_db/l_genre_genre
flozz_daily_mix-0.5.1.dist-info/entry_points.txt
flozz_daily_mix-0.5.1.dist-info/licenses/COPYING
flozz_daily_mix-0.5.1.dist-info/WHEEL
flozz_daily_mix-0.5.1.dist-info/METADATA
flozz_daily_mix-0.5.1.dist-info/RECORD
