Metadata-Version: 2.4
Name: flozz-daily-mix
Version: 0.5.1
Summary: Generates thematic playlists like Spotify's Daily Mix from a Subsonic API
Keywords: playlist,subsonic,owncloud,nextcloud,music
Author: Fabien LOISON
Requires-Python: >=3.9
License-Expression: AGPL-3.0-or-later
License-File: COPYING
Requires-Dist: nox ; extra == "dev"
Requires-Dist: flit ; extra == "dev"
Requires-Dist: black ; extra == "dev"
Requires-Dist: flake8 ; extra == "dev"
Requires-Dist: flake8-pyproject ; extra == "dev"
Requires-Dist: validate-pyproject ; extra == "dev"
Requires-Dist: pytest ; extra == "dev"
Project-URL: Chat, https://discord.gg/P77sWhuSs4
Project-URL: changelog, https://github.com/flozz/daily-mix?tab=readme-ov-file#changelog
Project-URL: documentation, https://github.com/flozz/daily-mix/blob/master/README.rst
Project-URL: donate, https://github.com/flozz/daily-mix?tab=readme-ov-file#support-this-project
Project-URL: issues, https://github.com/flozz/daily-mix/issues
Project-URL: source, https://github.com/flozz/daily-mix
Provides-Extra: dev
